pdxtend/__init__.py
pdxtend/excel_reader.py
pdxtend/exceptions.py
pdxtend-0.1.3.dist-info/METADATA
pdxtend-0.1.3.dist-info/WHEEL
pdxtend-0.1.3.dist-info/top_level.txt
pdxtend-0.1.3.dist-info/RECORD
